cautil/__init__.py
cautil/utils/__init__.py
cautil/utils/authorization/Cognito.py
cautil/utils/authorization/DB.py
cautil/utils/authorization/__init__.py
cautil/utils/email/SES.py
cautil/utils/email/SMTP.py
cautil/utils/email/SendGrid.py
cautil/utils/email/__init__.py
cautil/utils/notification/SNS.py
cautil/utils/notification/__init__.py
cautil/utils/storage/MinIO.py
cautil/utils/storage/S3.py
cautil/utils/storage/__init__.py
cautil_init/__init__.py
cautil_init/package.py
cautil_init/sample2.py
cautil_init/sample_app.py
cautil-2.4.dist-info/METADATA
cautil-2.4.dist-info/WHEEL
cautil-2.4.dist-info/top_level.txt
cautil-2.4.dist-info/RECORD
