Metadata-Version: 2.1
Name: cautil
Version: 2.4
Summary: The UTILITY for Cloud Agnostic
Home-page: http://github.com/whirldata/cautil
Author: Whirldata
Author-email: info@whirldatascience.com.com
License: MIT
Platform: UNKNOWN
